tkosui/__init__.py
tkosui-1.1.0.dist-info/METADATA
tkosui-1.1.0.dist-info/WHEEL
tkosui-1.1.0.dist-info/top_level.txt
tkosui-1.1.0.dist-info/RECORD
